polyline_ruler-0.0.6.dist-info/METADATA
polyline_ruler-0.0.6.dist-info/RECORD
polyline_ruler-0.0.6.dist-info/WHEEL
polyline_ruler-0.0.6.dist-info/licenses/LICENSE
polyline_ruler/_core.cpython-39-aarch64-linux-gnu.so
polyline_ruler/__init__.py
polyline_ruler/py.typed
polyline_ruler/_core/__init__.pyi
polyline_ruler/_core/tf.pyi
